{
  "content": "t = taskMgr.doMethodLater(DG.DIRECT_FLASH_DURATION,\n                                      # This is just a dummy task\n                                      self.flashDummy,\n                                      'flashNodePath',)\n            t.nodePath = nodePath\n            t.doneColor = doneColor\n            # This really does all the work\n            t.setUponDeath(self.flashDone)",
  "metadata": {
    "doc_type": "python",
    "doc_id": "doc_185",
    "parent": "processed_documents/context_documents/4b554dbd_DirectSession.json",
    "chunk_number": 3415
  }
}