{
  "content": "\"\"\"\nSlider Class: Velocity style controller for floating point values with\n               a label, entry (validated), and min/max slider\n\"\"\"\n\n__all__ = ['Slider', 'SliderWidget', 'rgbPanel']\n\nfrom .Valuator import Valuator, rgbPanel, VALUATOR_MINI, VALUATOR_FULL\nimport Pmw\nimport tkinter as tk",
  "metadata": {
    "doc_type": "python",
    "doc_id": "doc_189",
    "parent": "processed_documents/context_documents/409002c6_Slider.json",
    "chunk_number": 3500
  }
}