{
  "content": "if not hasKey and self.editor.animMgr.curveAnimation != {}:\n                self.editor.animMgr.curveAnimation[(self.nodePath[OG.OBJ_UID], self.curve[OG.OBJ_UID])] = \\\n                    (self.nodePath[OG.OBJ_UID], self.curve[OG.OBJ_UID], self.time)\n                self.editor.updateStatusReadout('Sucessfully saved to global animation list')\n\n    def OnExit(self, evt):\n        self.Destroy()\n        self.editor.ui.curveAnimMenuItem.Check(False)",
  "metadata": {
    "doc_type": "python",
    "doc_id": "doc_30",
    "parent": "processed_documents/context_documents/258ea79b_CurveAnimUI.json",
    "chunk_number": 472
  }
}