{
  "content": "Usually it's a performance advantage to keep this true. See\nTextNode::set_flatten_flags(). text-embed-graphic-key int 5 This is the decimal character number that, embedded in a string, is\nused to bracket the name of a model added to the TextPropertiesManager\nobject, to embed an arbitrary graphic image within a paragraph. text-encoding enum utf8 Specifies how international characters are represented in strings of\n8-byte characters presented to Panda. See\nTextEncoder::set_encoding(). text-flatten bool 1 Set this true to flatten text when it is generated, or false to keep\nit as a deep hierarchy. Usually it's a performance advantage to keep\nthis true, but this also depends on the setting of text-dynamic-merge.\nSee TextNode::set_flatten_flags(). text-hyphen-ratio double 0.7 If the rightmost whitespace character falls before this fraction of\nthe line, hyphenate a word to the right of that if possible. text-kerning bool 0 Set this true to enable kerning when the font provides kerning",
  "metadata": {
    "doc_type": "rst",
    "doc_id": "doc_543",
    "parent": "processed_documents/context_documents/ff9c6499_876ce29a_list-of-all-config-variables.json",
    "chunk_number": 6854
  }
}