{
  "content": "LightRampAttrib <light-ramps>: Enables HDR tone mapping or cartoon shading.\n\nMaterialAttrib <materials>: Changes the way the model reflects light.\n\nRenderModeAttrib: Used to enable wireframe rendering.\n\nRescaleNormalAttrib: Can disable the automatic correction of non-unit normals.\n\nShadeModelAttrib: Can cause the model to appear faceted instead of smooth.\n\nShaderAttrib <shaders>: Gives almost unlimited control, but difficult to use.\n\nStencilAttrib <stencil-attribute>: Causes the model to affect the stencil buffer, or be affected by the stencil buffer.\n\nTexGenAttrib <automatic-texture-coordinates>: Causes the system to synthesize texture coordinates for the model.\n\nTexMatrixAttrib <texture-transforms>: Alters the existing texture coordinates.\n\nTextureAttrib <texturing>: Applies a texture map to the model.\n\nTransparencyAttrib <transparency-and-blending>: Causes the model to be partially transparent.\n\nUndocumented",
  "metadata": {
    "doc_type": "rst",
    "doc_id": "doc_598",
    "parent": "processed_documents/context_documents/72495fc3_ee7ef0a6_list-of-all-attributes.json",
    "chunk_number": 7164
  }
}