{
  "content": "python\n\nlowPassFilter = AlphaTestAttrib.make(RenderAttrib.MLess,0.25)\n\ncpp\n\nCPT(RenderAttrib) low_pass_filter = AlphaTestAttrib::make(PandaCompareFunc::M_less, 0.25);\n\nAnd now, this attribute can be added to a node to enable the action.\n\npython\n\nnodePath.setAttrib(lowPassFilter)\n\ncpp\n\nnodePath.set_attrib(low_pass_filter);",
  "metadata": {
    "doc_type": "rst",
    "doc_id": "doc_671",
    "parent": "processed_documents/context_documents/85b935fd_a1fa5974_alpha-testing.json",
    "chunk_number": 7586
  }
}