{
  "content": "This code chunk configures the direct manipulation controls in a 3D modeling or visualization application by locking the camera roll axis, setting scaling based on the camera view, and defining a list of unpickable geometric guide elements to prevent accidental selection during object manipulation.\n\ndirect.cameraControl.lockRoll = True\n            direct.setFScaleWidgetByCam(1)\n\n            unpickables = [\n                \"z-guide\",\n                \"y-guide\",\n                \"x-guide\",\n                \"x-disc-geom\",\n                \"x-ring-line\",\n                \"x-post-line\",\n                \"y-disc-geom\",\n                \"y-ring-line\",\n                \"y-post-line\",\n                \"z-disc-geom\",\n                \"z-ring-line\",\n                \"z-post-line\",\n                \"centerLines\",\n                \"majorLines\",\n                \"minorLines\",\n                \"Sphere\",]\n\n            for unpickable in unpickables:\n                direct.addUnpickable(unpickable)",
  "metadata": {
    "doc_type": "python",
    "doc_id": "doc_13",
    "parent": "processed_documents/context_documents/b3c83735_WxPandaShell.json",
    "chunk_number": 188
  }
}