{
  "content": "The provided chunk defines an enum descriptor for `DexMergingStrategy` under `StandaloneConfig`, which specifies strategies for handling DEX file merging in an Android bundle configuration.\n\n_STANDALONECONFIG_DEXMERGINGSTRATEGY = _descriptor.EnumDescriptor(\n  name='DexMergingStrategy',\n  full_name='android.bundle.StandaloneConfig.DexMergingStrategy',\n  filename=None,\n  file=DESCRIPTOR,\n  create_key=_descriptor._internal_create_key,\n  values=[\n    _descriptor.EnumValueDescriptor(\n      name='MERGE_IF_NEEDED', index=0, number=0,\n      serialized_options=None,\n      type=None,\n      create_key=_descriptor._internal_create_key),\n    _descriptor.EnumValueDescriptor(\n      name='NEVER_MERGE', index=1, number=1,\n      serialized_options=None,\n      type=None,\n      create_key=_descriptor._internal_create_key),\n  ],\n  containing_type=None,\n  serialized_options=None,\n  serialized_start=1833,\n  serialized_end=1891,\n)\n_sym_db.RegisterEnumDescriptor(_STANDALONECONFIG_DEXMERGINGSTRATEGY)",
  "metadata": {
    "doc_type": "python",
    "doc_id": "doc_142",
    "parent": "processed_documents/context_documents/a7faf737_config_pb2.json",
    "chunk_number": 2558
  }
}