{
  "content": "The provided code chunk defines initial options for a DirectGUI widget, including properties like position, scale, color, event suppression settings, and editability. These options are merged with user-provided keyword arguments during initialization to set the widget's behavior and appearance upon creation.\n\n**Context:**\n\nThis chunk is part of the initialization process where default options are defined and merged with provided keyword arguments for a DirectGUI widget. It sets up initial properties such as position, scale, color, event handling, and editability, ensuring that the widget has sensible defaults while allowing customization.\n\n('guiId',          None,         DGG.INITOPT),\n            # Initial pos/scale of the widget\n            ('pos',            None,         DGG.INITOPT),\n            ('hpr',            None,         DGG.INITOPT),\n            ('scale',          None,         DGG.INITOPT),\n            ('color',          None,         DGG.INITOPT),\n            # Do events pass through this widget?\n            ('suppressMouse',  1,            DGG.INITOPT),\n            ('suppressKeys',   0,            DGG.INITOPT),\n            ('enableEdit',     1,            DGG.INITOPT),\n        )\n        # Merge keyword options with default options\n        self.defineoptions(kw, optiondefs)",
  "metadata": {
    "doc_type": "python",
    "doc_id": "doc_78",
    "parent": "processed_documents/context_documents/414a65d1_DirectGuiBase.json",
    "chunk_number": 1408
  }
}