{
  "content": "This code chunk defines methods for showing specific UI handles (`x-`, `y-`, `z-` post, ring, disc, scale) and controlling the visibility of guide lines. It is likely part of a class managing 3D object manipulation or scene interaction in a viewer or editor, where these handles are used to assist users in adjusting object placement or scaling.\n\ndef showHandle(self, handle):\n        if handle == 'x-post':\n            self.xPost.show()\n        elif handle == 'x-ring':\n            self.xRing.show()\n        elif handle == 'x-disc':\n            self.xDisc.show()\n        elif handle == 'x-scale':\n            self.xScale.show()\n        elif handle == 'y-post':\n            self.yPost.show()\n        elif handle == 'y-ring':\n            self.yRing.show()\n        elif handle == 'y-disc':\n            self.yDisc.show()\n        elif handle == 'y-scale':\n            self.yScale.show()\n        elif handle == 'z-post':\n            self.zPost.show()\n        elif handle == 'z-ring':\n            self.zRing.show()\n        elif handle == 'z-disc':\n            self.zDisc.show()\n        elif handle == 'z-scale':\n            self.zScale.show()\n\n    def showGuides(self):\n        self.guideLines.show()\n\n    def hideGuides(self):\n        self.guideLines.hide()",
  "metadata": {
    "doc_type": "python",
    "doc_id": "doc_179",
    "parent": "processed_documents/context_documents/4f678cc8_DirectManipulation.json",
    "chunk_number": 3273
  }
}