{
  "content": "This chunk details specific particle emitters including PointEmitter, RectangleEmitter, RingEmitter, SphereSurfaceEmitter, and SphereVolumeEmitter, describing their unique parameters and custom mode behavior.\n\nPointEmitter\n\nVariable Definition Values location Location of outer point (x, y, z)\n\nCustom mode generates particles with no initial velocity.\n\nRectangleEmitter\n\nVariable Definition Values minBound 2D point defining the rectangle (x, z) maxBound 2D point defining the rectangle (x, z)\n\nCustom mode generates particles with no initial velocity.\n\nRingEmitter\n\nVariable Definition Values radius Radius of disc [0, infinity) angle Particle launch angle [0, 360]\n\nCustom mode uses the second parameter to emit particles at an angle with respect to the vector from the ring center to the spawn point. 0 degrees emits particles away from the center, and 180 degrees emits particles into the center.\n\nSphereSurfaceEmitter\n\nVariable Definition Values radius Radius of sphere [0, infinity)\n\nCustom mode generates particles with no initial velocity.\n\nSphereVolumeEmitter\n\nVariable Definition Values radius Radius of sphere [0, infinity)",
  "metadata": {
    "doc_type": "rst",
    "doc_id": "doc_481",
    "parent": "processed_documents/context_documents/bca0c7c6_e03f3d82_emitters.json",
    "chunk_number": 6433
  }
}