{
  "content": "The provided code defines two new protocol buffer message types: `RawString` and `StyledString`, with the latter containing an inner `Span` class. These messages are part of the same module as other existing message definitions in the document, such as `StyleString` and `UntranslatableSection`. The chunk should be situated among these message type definitions to maintain logical grouping and improve search retrieval within the overall code structure.\n\nRawString = _reflection.GeneratedProtocolMessageType('RawString', (_message.Message,), {\n  'DESCRIPTOR' : _RAWSTRING,\n  '__module__' : 'frameworks.base.tools.aapt2.Resources_pb2'\n  # @@protoc_insertion_point(class_scope:aapt.pb.RawString)\n  })\n_sym_db.RegisterMessage(RawString)\n\nStyledString = _reflection.GeneratedProtocolMessageType('StyledString', (_message.Message,), {\n\n  'Span' : _reflection.GeneratedProtocolMessageType('Span', (_message.Message,), {\n    'DESCRIPTOR' : _STYLEDSTRING_SPAN,\n    '__module__' : 'frameworks.base.tools.aapt2.Resources_pb2'\n    # @@protoc_insertion_point(class_scope:aapt.pb.StyledString.Span)\n    })\n  ,\n  'DESCRIPTOR' : _STYLEDSTRING,\n  '__module__' : 'frameworks.base.tools.aapt2.Resources_pb2'\n  # @@protoc_insertion_point(class_scope:aapt.pb.StyledString)\n  })\n_sym_db.RegisterMessage(StyledString)\n_sym_db.RegisterMessage(StyledString.Span)",
  "metadata": {
    "doc_type": "python",
    "doc_id": "doc_138",
    "parent": "processed_documents/context_documents/e963edbe_Resources_pb2.json",
    "chunk_number": 2403
  }
}