{
  "content": "The chunk consists of three methods (`setBackground`, `highlightWidget`, and `restoreWidget`) within a widget-related class (likely `Floater`), which modify the widget's appearance by changing its background color or the fill color of a specific item ('floater').\n\ndef setBackground(self):\n        self._widget['background'] = self['background']\n\n    def highlightWidget(self, event):\n        self._widget.itemconfigure('floater', fill = 'black')\n\n    def restoreWidget(self, event):\n        self._widget.itemconfigure('floater', fill = 'grey50')",
  "metadata": {
    "doc_type": "python",
    "doc_id": "doc_195",
    "parent": "processed_documents/context_documents/1702bab6_Floater.json",
    "chunk_number": 3620
  }
}