{
  "content": "The chunk contains methods for initializing attributes (`self.mopath` and `self.node`), cleaning up resources with `destroy()`, and defining the `_doMopath()` method to update a node's position along a motion path at a given time `t`.\n\nself.mopath = mopath\n        self.node = node\n\n    def destroy(self):\n        \"\"\"Cleanup to avoid a garbage cycle.\"\"\"\n        self.function = None\n\n    def __doMopath(self, t):\n        \"\"\"\n        Go to time t\n        \"\"\"\n        self.mopath.goTo(self.node, t)",
  "metadata": {
    "doc_type": "python",
    "doc_id": "doc_158",
    "parent": "processed_documents/context_documents/7e2ecfd2_MopathInterval.json",
    "chunk_number": 2800
  }
}