{
  "content": "The provided code chunk is a crucial part of the `ReferrerSearch` class's functionality, which is designed to identify and track all referrers of a specified object in Python. This particular section is responsible for checking if an object has already been visited during the search process. If it has, it raises a `StopIteration` to prevent revisiting the same object and potential infinite loops. The code then marks the object as visited by adding its unique identifier (`id(at)`) to the `self.visited` set, ensuring each object is processed only once.\n\nif id(at) in self.visited:\n            # don't continue down this path\n            raise StopIteration\n\n        # mark our progress after checking goal\n        self.visited.add(id(at))",
  "metadata": {
    "doc_type": "python",
    "doc_id": "doc_279",
    "parent": "processed_documents/context_documents/358f23e5_ReferrerSearch.json",
    "chunk_number": 4816
  }
}