{
  "content": "The document provides an overview of a package containing `.ShowBase`, highlighting its role as an essential framework for developing graphical applications by managing display initialization, input device configuration, and scene graph construction.\n\n\"\"\" This package contains `.ShowBase`, an application framework responsible\nfor opening a graphical display, setting up input devices and creating\nthe scene graph. \"\"\"",
  "metadata": {
    "doc_type": "python",
    "doc_id": "doc_248",
    "parent": "processed_documents/context_documents/7a584ba6___init__.json",
    "chunk_number": 4364
  }
}