{
  "content": "This section provides instructions for installing and using a custom Maya-Panda script to tag objects with specific types, allowing users to customize their workflow within Maya for better asset management in Panda3D projects.\n\nInstallation\n\nOpen up maya's script editor (Window>General Editors>Script Editor)\n\nOpen the script in the editor and execute it (Ctrl+Enter or Script>Execute)\n\nType \"eggObjectFlags()\" at the script editor and select the text.\n\nMiddle mouse drag the selection into your custom shelf.\n\nOptional: go to the shelf editor and give it a custom icon/name\n\nUsage\n\nSelect the objects that you want to tag and press the shelf script.\n\nSet the object type by going to the channel box of the object, there should be a new attribute called Egg Object TypesN.\n\nSet the object type to the desired value.",
  "metadata": {
    "doc_type": "rst",
    "doc_id": "doc_452",
    "parent": "processed_documents/context_documents/3f533d33_a979858b_converting-from-maya.json",
    "chunk_number": 6288
  }
}