{
  "content": "The provided chunk is the introductory section of a Python module defining an `EventGroup` class. It includes the module's docstring, `__all__` export declaration, and essential imports from DirectShowbase libraries. This setup establishes the module's core functionality by importing necessary classes for event handling and object management.\n\n\"\"\"This module defines the EventGroup class.\"\"\"\n\n__all__ = ['EventGroup']\n\nfrom direct.showbase import DirectObject\nfrom direct.showbase.PythonUtil import SerialNumGen, Functor\nfrom direct.showbase.MessengerGlobal import messenger",
  "metadata": {
    "doc_type": "python",
    "doc_id": "doc_253",
    "parent": "processed_documents/context_documents/3322f876_EventGroup.json",
    "chunk_number": 4440
  }
}