{
  "content": "bMethod = \"PPBLENDCUBIC\"\n            file.write(targ + '.renderer.setAlphaBlendMethod(BaseParticleRenderer.' + bMethod + ')\\n')\n            file.write(targ + '.renderer.setAlphaDisable(%d)\\n' % self.renderer.getAlphaDisable())\n            # Save the color blending to file\n            cbmLut = ('MNone','MAdd','MSubtract','MInvSubtract','MMin','MMax')\n            cboLut = ('OZero','OOne','OIncomingColor','OOneMinusIncomingColor','OFbufferColor',\n                      'OOneMinusFbufferColor','OIncomingAlpha','OOneMinusIncomingAlpha',\n                      'OFbufferAlpha','OOneMinusFbufferAlpha','OConstantColor',\n                      'OOneMinusConstantColor','OConstantAlpha','OOneMinusConstantAlpha',\n                      'OIncomingColorSaturate')\n            cbAttrib = self.renderer.getRenderNode().getAttrib(ColorBlendAttrib.getClassType())\n            if cbAttrib:\n                cbMode = cbAttrib.getMode()\n                if cbMode > 0:",
  "metadata": {
    "doc_type": "python",
    "doc_id": "doc_69",
    "parent": "processed_documents/context_documents/b3935c67_Particles.json",
    "chunk_number": 1286
  }
}