{
  "content": "# Register the extension methods for NodePath.\nfrom direct.extensions_native import NodePath_extensions # pylint: disable=unused-import\n\n# This needs to be available early for DirectGUI imports\nfrom typing import Any\nbuiltins: Any  # Tell mypy not to worry about us setting attributes on builtins\nimport sys\nimport builtins\nbuiltins.config = DConfig",
  "metadata": {
    "doc_type": "python",
    "doc_id": "doc_283",
    "parent": "processed_documents/context_documents/be1afc59_ShowBase.json",
    "chunk_number": 4846
  }
}