{
  "content": "_PRIMITIVE.oneofs_by_name['oneof_value'].fields.append(\n  _PRIMITIVE.fields_by_name['float_value'])\n_PRIMITIVE.fields_by_name['float_value'].containing_oneof = _PRIMITIVE.oneofs_by_name['oneof_value']\n_PRIMITIVE.oneofs_by_name['oneof_value'].fields.append(\n  _PRIMITIVE.fields_by_name['dimension_value'])\n_PRIMITIVE.fields_by_name['dimension_value'].containing_oneof = _PRIMITIVE.oneofs_by_name['oneof_value']\n_PRIMITIVE.oneofs_by_name['oneof_value'].fields.append(\n  _PRIMITIVE.fields_by_name['fraction_value'])\n_PRIMITIVE.fields_by_name['fraction_value'].containing_oneof = _PRIMITIVE.oneofs_by_name['oneof_value']\n_PRIMITIVE.oneofs_by_name['oneof_value'].fields.append(\n  _PRIMITIVE.fields_by_name['int_decimal_value'])\n_PRIMITIVE.fields_by_name['int_decimal_value'].containing_oneof = _PRIMITIVE.oneofs_by_name['oneof_value']\n_PRIMITIVE.oneofs_by_name['oneof_value'].fields.append(\n  _PRIMITIVE.fields_by_name['int_hexadecimal_value'])",
  "metadata": {
    "doc_type": "python",
    "doc_id": "doc_138",
    "parent": "processed_documents/context_documents/e963edbe_Resources_pb2.json",
    "chunk_number": 2385
  }
}