{
  "content": "unspecified Default severity of this notify category notify-level-physics enum unspecified Default severity of this notify category notify-level-pipeline enum unspecified Default severity of this notify category notify-level-png enum unspecified Default severity of this notify category notify-level-pnm enum unspecified Default severity of this notify category notify-level-pnmimage enum unspecified Default severity of this notify category notify-level-pnmtext enum unspecified Default severity of this notify category notify-level-portal enum unspecified Default severity of this notify category notify-level-prc enum unspecified Default severity of this notify category notify-level-pstats enum unspecified Default severity of this notify category notify-level-ptloader enum unspecified Default severity of this notify category notify-level-recorder enum unspecified Default severity of this notify category notify-level-sgi enum unspecified Default severity of this notify category",
  "metadata": {
    "doc_type": "rst",
    "doc_id": "doc_543",
    "parent": "processed_documents/context_documents/ff9c6499_876ce29a_list-of-all-config-variables.json",
    "chunk_number": 6817
  }
}