{
  "content": "\\x01(\\x0b\\x32#.android.bundle.SdkVersionTargeting\\x12H\\n\\x18\\x64\\x65vice_feature_targeting\\x18\\x02 \\x03(\\x0b\\x32&.android.bundle.DeviceFeatureTargeting\\x12H\\n\\x18user_countries_targeting\\x18\\x03 \\x01(\\x0b\\x32&.android.bundle.UserCountriesTargeting\\x12J\\n\\x16\\x64\\x65vice_group_targeting\\x18\\x05 \\x01(\\x0b\\x32*.android.bundle.DeviceGroupModuleTargetingJ\\x04\\x08\\x04\\x10\\x05\\\"@\\n\\x16UserCountriesTargeting\\x12\\x15\\n\\rcountry_codes\\x18\\x01 \\x03(\\t\\x12\\x0f\\n\\x07\\x65xclude\\x18\\x02 \\x01(\\x08\\\"\\xfd\\x01\\n\\rScreenDensity\\x12\\x43\\n\\rdensity_alias\\x18\\x01 \\x01(\\x0e\\x32*.android.bundle.ScreenDensity.DensityAliasH\\x00\\x12\\x15\\n\\x0b\\x64\\x65nsity_dpi\\x18\\x02",
  "metadata": {
    "doc_type": "python",
    "doc_id": "doc_141",
    "parent": "processed_documents/context_documents/8f498409_targeting_pb2.json",
    "chunk_number": 2467
  }
}