{
  "content": "\"\"\"OnscreenText module: contains the OnscreenText class.\n\nSee the :ref:`onscreentext` page in the programming manual for explanation of\nthis class.\n\"\"\"\n\n__all__ = ['OnscreenText', 'Plain', 'ScreenTitle', 'ScreenPrompt', 'NameConfirm', 'BlackOnWhite']\n\nfrom panda3d.core import LColor, Mat4, NodePath, Point3, TextNode, TextProperties, Vec3\nfrom . import DirectGuiGlobals as DGG\nimport warnings\n\n## These are the styles of text we might commonly see.  They set the\n## overall appearance of the text according to one of a number of\n## pre-canned styles.  You can further customize the appearance of the\n## text by specifying individual parameters as well.\nPlain = 1\nScreenTitle = 2\nScreenPrompt = 3\nNameConfirm = 4\nBlackOnWhite = 5",
  "metadata": {
    "doc_type": "python",
    "doc_id": "doc_82",
    "parent": "processed_documents/context_documents/de45d2f7_OnscreenText.json",
    "chunk_number": 1458
  }
}