{
  "content": "def startRecording(self):\n        self.accept('escape', self.stopRecording)\n        for fixture in self.fixtures:\n            fixture[6] = 'Recording'\n        self.b_setFixtures(self.fixtures)\n\n    def stopRecording(self):\n        self.ignore('escape')\n        for fixture in self.fixtures:\n            fixture[6] = 'Standby'\n        self.b_setFixtures(self.fixtures)",
  "metadata": {
    "doc_type": "python",
    "doc_id": "doc_331",
    "parent": "processed_documents/context_documents/3deb3265_DistributedCameraOV.json",
    "chunk_number": 5650
  }
}